{
  "name": "Pastel: Rosé",
  "type": "dark",
  "semanticHighlighting": true,
  "colors": {
    "editor.background": "#191724",
    "editor.foreground": "#e0def4",
    "editorLineNumber.foreground": "#737182",
    "editorLineNumber.activeForeground": "#c4a7e7",
    "editor.selectionBackground": "#c4a7e742",
    "editor.lineHighlightBackground": "#272531",
    "editorCursor.foreground": "#c4a7e7",
    "editor.findMatchBackground": "#c4a7e766",
    "editor.findMatchHighlightBackground": "#c4a7e738",
    "editorWhitespace.foreground": "#e0def41a",
    "editorIndentGuide.background1": "#e0def414",
    "editorIndentGuide.activeBackground1": "#e0def438",
    "editorBracketMatch.border": "#c4a7e7",
    "activityBar.background": "#12111a",
    "activityBar.foreground": "#c4a7e7",
    "activityBar.inactiveForeground": "#737182",
    "activityBarBadge.background": "#c4a7e7",
    "activityBarBadge.foreground": "#1a1a1a",
    "sideBar.background": "#16141f",
    "sideBar.foreground": "#e0def4",
    "sideBarTitle.foreground": "#c4a7e7",
    "sideBarSectionHeader.background": "#191724",
    "statusBar.background": "#12111a",
    "statusBar.foreground": "#e0def4",
    "statusBar.noFolderBackground": "#12111a",
    "titleBar.activeBackground": "#12111a",
    "titleBar.activeForeground": "#e0def4",
    "titleBar.inactiveBackground": "#12111a",
    "titleBar.inactiveForeground": "#737182",
    "editorGroupHeader.tabsBackground": "#171520",
    "tab.activeBackground": "#191724",
    "tab.activeForeground": "#c4a7e7",
    "tab.inactiveBackground": "#171520",
    "tab.inactiveForeground": "#737182",
    "tab.activeBorderTop": "#c4a7e7",
    "tab.border": "#171520",
    "panel.background": "#16141f",
    "panelTitle.activeForeground": "#c4a7e7",
    "terminal.background": "#191724",
    "terminal.foreground": "#e0def4",
    "button.background": "#c4a7e7",
    "button.foreground": "#1a1a1a",
    "button.hoverBackground": "#cbb2ea",
    "input.background": "#12111a",
    "input.foreground": "#e0def4",
    "input.placeholderForeground": "#737182",
    "dropdown.background": "#12111a",
    "focusBorder": "#c4a7e7",
    "list.activeSelectionBackground": "#c4a7e742",
    "list.activeSelectionForeground": "#e0def4",
    "list.hoverBackground": "#272531",
    "list.inactiveSelectionBackground": "#c4a7e724",
    "badge.background": "#c4a7e7",
    "badge.foreground": "#1a1a1a",
    "scrollbarSlider.background": "#e0def429",
    "scrollbarSlider.hoverBackground": "#e0def442",
    "scrollbarSlider.activeBackground": "#e0def45c",
    "editorWidget.background": "#12111a",
    "editorSuggestWidget.selectedBackground": "#c4a7e742",
    "selection.background": "#c4a7e74d"
  },
  "tokenColors": [
    {
      "scope": "comment",
      "settings": {
        "foreground": "#6e6a86",
        "fontStyle": "italic"
      }
    },
    {
      "scope": [
        "string",
        "string.quoted",
        "string.template"
      ],
      "settings": {
        "foreground": "#9ccfd8"
      }
    },
    {
      "scope": [
        "constant.numeric",
        "constant.language",
        "constant.character"
      ],
      "settings": {
        "foreground": "#f6c177"
      }
    },
    {
      "scope": [
        "keyword",
        "keyword.control",
        "storage",
        "storage.type",
        "storage.modifier"
      ],
      "settings": {
        "foreground": "#31748f"
      }
    },
    {
      "scope": [
        "entity.name.function",
        "support.function",
        "meta.function-call.generic"
      ],
      "settings": {
        "foreground": "#ebbcba"
      }
    },
    {
      "scope": [
        "variable",
        "meta.definition.variable.name",
        "variable.other.readwrite"
      ],
      "settings": {
        "foreground": "#e0def4"
      }
    },
    {
      "scope": [
        "variable.parameter",
        "parameter"
      ],
      "settings": {
        "foreground": "#bcbacf"
      }
    },
    {
      "scope": [
        "entity.name.type",
        "support.type",
        "support.class",
        "entity.name.namespace"
      ],
      "settings": {
        "foreground": "#c4a7e7"
      }
    },
    {
      "scope": [
        "variable.other.property",
        "variable.other.object.property",
        "support.variable.property",
        "meta.object-literal.key"
      ],
      "settings": {
        "foreground": "#eb6f92"
      }
    },
    {
      "scope": "keyword.operator",
      "settings": {
        "foreground": "#31748f"
      }
    },
    {
      "scope": [
        "entity.name.tag",
        "punctuation.definition.tag"
      ],
      "settings": {
        "foreground": "#31748f"
      }
    },
    {
      "scope": [
        "entity.other.attribute-name"
      ],
      "settings": {
        "foreground": "#ebbcba"
      }
    },
    {
      "scope": [
        "constant.other.color",
        "support.constant"
      ],
      "settings": {
        "foreground": "#f6c177"
      }
    },
    {
      "scope": "entity.name.type.class",
      "settings": {
        "foreground": "#c4a7e7",
        "fontStyle": "bold"
      }
    },
    {
      "scope": [
        "markup.bold"
      ],
      "settings": {
        "fontStyle": "bold"
      }
    },
    {
      "scope": [
        "markup.italic"
      ],
      "settings": {
        "fontStyle": "italic"
      }
    },
    {
      "scope": [
        "markup.heading"
      ],
      "settings": {
        "foreground": "#c4a7e7",
        "fontStyle": "bold"
      }
    },
    {
      "scope": [
        "invalid"
      ],
      "settings": {
        "foreground": "#191724",
        "background": "#31748f"
      }
    }
  ],
  "semanticTokenColors": {
    "function": "#ebbcba",
    "method": "#ebbcba",
    "class": "#c4a7e7",
    "property": "#eb6f92",
    "parameter": "#bcbacf",
    "variable": "#e0def4"
  }
}
